qlep/__init__.py
qlep/draw.py
qlep/func.py
qlep/basic/__init__.py
qlep/basic/dummy.py
qlep/basic/ghzstate.py
qlep/basic/wstate.py
qlep/core/__init__.py
qlep/core/committeetypes.py
qlep/core/electiontypes.py
qlep/core/providers.py
qlep/core/qlep.py
qlep/core/qpos.py
qlep/core/wcftypes.py
qlep/ecc/__init__.py
qlep/ecc/foldhamming.py
qlep/ecc/foldwalsh.py
qlep/ecc/hamming.py
qlep/ecc/walsh.py
qlep/wcf/__init__.py
qlep-0.1.2.dist-info/LICENSE.txt
qlep-0.1.2.dist-info/METADATA
qlep-0.1.2.dist-info/WHEEL
qlep-0.1.2.dist-info/top_level.txt
qlep-0.1.2.dist-info/RECORD
