Metadata-Version: 2.1
Name: qlep
Version: 0.1.2
Summary: Quantum Leader Election Protocols
Home-page: https://github.com/sdcioc/QuantumLeaderElection
Author: Stefan-Dan Ciocirlan (sdcioc)
Author-email: stefan_dan@xn--ciocirlan-o2a.ro
License: EUPL-1.2
Platform: UNKNOWN
Classifier: Intended Audience :: Developers
Classifier: Intended Audience :: Science/Research
Classifier: Development Status :: 4 - Beta
Classifier: License :: OSI Approved :: European Union Public
Classifier: Operating System :: Microsoft :: Windows
Classifier: Operating System :: MacOS
Classifier: Operating System :: POSIX :: Linux
Classifier: Programming Language :: Python :: 3
Classifier: Programming Language :: Python :: 3.6
Classifier: Programming Language :: Python :: 3.7
Classifier: Programming Language :: Python :: 3.8
Classifier: Programming Language :: Python :: 3.9
Classifier: Programming Language :: Python :: 3.10
Classifier: Programming Language :: Python :: 3.11
Classifier: Topic :: Scientific/Engineering
Requires-Python: >=3.6, <4
License-File: LICENSE.txt
Requires-Dist: amazon-braket-sdk
Requires-Dist: matplotlib
Requires-Dist: numpy
Requires-Dist: qiskit-aer
Requires-Dist: qiskit-ibm-provider (==0.5.3)
Requires-Dist: qiskit[visualization]
Requires-Dist: qiskit-braket-provider
Requires-Dist: qiskit-pqcee-provider
